nomoji/__init__.py
nomoji-0.0.5.dist-info/LICENSE
nomoji-0.0.5.dist-info/METADATA
nomoji-0.0.5.dist-info/WHEEL
nomoji-0.0.5.dist-info/top_level.txt
nomoji-0.0.5.dist-info/RECORD
