Metadata-Version: 2.1
Name: nomoji
Version: 0.0.5
Summary: Silly Python Package to print digits using emojis
Home-page: https://github.com/leriomaggio/emoji-numbers/
Author: Valerio Maggio
Author-email: vmaggio@anaconda.com
Classifier: License :: OSI Approved :: MIT License
Classifier: Environment :: Console
Classifier: Intended Audience :: Developers
Classifier: Intended Audience :: Science/Research
Classifier: Programming Language :: Python :: 3
Requires-Python: >=3.6
License-File: LICENSE
